ufal.chu_liu_edmonds.libs/libgcc_s-4e37474d.so.1
ufal.chu_liu_edmonds.libs/libstdc++-fd9f4683.so.6.0.28
ufal/__init__.py
ufal/chu_liu_edmonds/_chu_liu_edmonds.cpython-37m-aarch64-linux-gnu.so
ufal/chu_liu_edmonds/__init__.py
ufal.chu_liu_edmonds-1.0.3.dist-info/RECORD
ufal.chu_liu_edmonds-1.0.3.dist-info/WHEEL
ufal.chu_liu_edmonds-1.0.3.dist-info/METADATA
ufal.chu_liu_edmonds-1.0.3.dist-info/top_level.txt
ufal.chu_liu_edmonds-1.0.3.dist-info/LICENSE
