Metadata-Version: 2.1
Name: ufal.chu_liu_edmonds
Version: 1.0.3
Summary: Bindings to Chu-Liu-Edmonds algorithm from TurboParser
Home-page: https://github.com/ufal/chu_liu_edmonds
Author: Milan Straka
Author-email: straka@ufal.mff.cuni.cz
License: GPLv3
Classifier: Development Status :: 5 - Production/Stable
Classifier: License :: OSI Approved :: GNU General Public License v3 (GPLv3)
Classifier: Programming Language :: C++
Classifier: Programming Language :: Python
Classifier: Programming Language :: Python :: 3
Classifier: Topic :: Software Development :: Libraries
License-File: LICENSE
